risa_framework/__init__.py
risa_framework-1.0.0.dist-info/METADATA
risa_framework-1.0.0.dist-info/WHEEL
risa_framework-1.0.0.dist-info/entry_points.txt
risa_framework-1.0.0.dist-info/top_level.txt
risa_framework-1.0.0.dist-info/RECORD
