Metadata-Version: 2.4
Name: risa-framework
Version: 1.0.0
Summary: Recursive Identity Symbolic Arithmetic (RISA) - Revolutionary mathematical framework
Home-page: https://github.com/travis-miner/risa-framework
Author: Travis Miner
Author-email: travis.miner@architect.com
License: MIT
Project-URL: Bug Tracker, https://github.com/travis-miner/risa-framework/issues
Project-URL: Documentation, https://risa-framework.readthedocs.io/
Project-URL: Source Code, https://github.com/travis-miner/risa-framework
Keywords: mathematics,physics,consciousness,recursive,algebra,quantum,rzda,risa,zero-division,theoretical-physics,ai-consciousness
Platform: any
Classifier: Development Status :: 4 - Beta
Classifier: Intended Audience :: Science/Research
Classifier: Intended Audience :: Developers
Classifier: License :: OSI Approved :: MIT License
Classifier: Operating System :: OS Independent
Classifier: Programming Language :: Python :: 3
Classifier: Programming Language :: Python :: 3.8
Classifier: Programming Language :: Python :: 3.9
Classifier: Programming Language :: Python :: 3.10
Classifier: Programming Language :: Python :: 3.11
Classifier: Programming Language :: Python :: 3.12
Classifier: Topic :: Scientific/Engineering :: Mathematics
Classifier: Topic :: Scientific/Engineering :: Physics
Classifier: Topic :: Scientific/Engineering :: Artificial Intelligence
Classifier: Topic :: Software Development :: Libraries :: Python Modules
Requires-Python: >=3.8
Provides-Extra: dev
Requires-Dist: pytest>=6.0; extra == "dev"
Requires-Dist: pytest-cov>=2.0; extra == "dev"
Requires-Dist: black>=21.0; extra == "dev"
Requires-Dist: flake8>=3.8; extra == "dev"
Requires-Dist: mypy>=0.800; extra == "dev"
Requires-Dist: sphinx>=4.0; extra == "dev"
Requires-Dist: sphinx-rtd-theme>=1.0; extra == "dev"
Provides-Extra: docs
Requires-Dist: sphinx>=4.0; extra == "docs"
Requires-Dist: sphinx-rtd-theme>=1.0; extra == "docs"
Requires-Dist: myst-parser>=0.15; extra == "docs"
Provides-Extra: examples
Requires-Dist: matplotlib>=3.3; extra == "examples"
Requires-Dist: numpy>=1.20; extra == "examples"
Requires-Dist: scipy>=1.7; extra == "examples"
Requires-Dist: jupyter>=1.0; extra == "examples"
Dynamic: author
Dynamic: author-email
Dynamic: classifier
Dynamic: description
Dynamic: description-content-type
Dynamic: home-page
Dynamic: keywords
Dynamic: license
Dynamic: platform
Dynamic: project-url
Dynamic: provides-extra
Dynamic: requires-python
Dynamic: summary
